README.rst
setup.py
properform/__init__.py
properform/__main__.py
properform/memory_leak.py
properform/profile.py
properform/properform.py
properform/travis.py
properform.egg-info/PKG-INFO
properform.egg-info/SOURCES.txt
properform.egg-info/dependency_links.txt
properform.egg-info/requires.txt
properform.egg-info/top_level.txt