Metadata-Version: 1.1
Name: properform
Version: 0.1.0
Summary: Submit profile data to properform.
Home-page: http://github.com/ibelie/properform/python
Author: joungtao
Author-email: joungtao@gmail.com
License: MIT License
Keywords: profile,properform
Platform: UNKNOWN
Classifier: Development Status :: 4 - Beta
Classifier: Environment :: Console
Classifier: Natural Language :: English
Classifier: Operating System :: OS Independent
Classifier: License :: OSI Approved :: MIT License
Classifier: Intended Audience :: Developers
Classifier: Intended Audience :: Science/Research
Classifier: Intended Audience :: Education
Classifier: Topic :: Software Development :: Libraries
Classifier: Programming Language :: Python :: 2.7
Classifier: Programming Language :: Python :: 3.6
